encrustable/__init__.py
encrustable/examples/__init__.py
encrustable/examples/option.py
encrustable/examples/panic.py
encrustable/examples/result.py
encrustable/option.py
encrustable/panic.py
encrustable/py.typed
encrustable/result.py
encrustable-1.0.0.post2.dist-info/LICENSE
encrustable-1.0.0.post2.dist-info/METADATA
encrustable-1.0.0.post2.dist-info/WHEEL
encrustable-1.0.0.post2.dist-info/RECORD
