Metadata-Version: 2.3
Name: encrustable
Version: 1.0.0.post2
Summary: Basic components of Rust's type system magic in Python
License: GPL-3.0-or-later
Author: Artur Ciesielski
Author-email: artur.ciesielski@gmail.com
Requires-Python: >=3.12,<4.0
Classifier: Development Status :: 5 - Production/Stable
Classifier: Intended Audience :: Developers
Classifier: Operating System :: OS Independent
Classifier: Topic :: Software Development :: Libraries :: Application Frameworks
Classifier: Topic :: Software Development :: Libraries :: Python Modules
Classifier: Typing :: Typed
Project-URL: Documentation, https://arcanery.gitlab.io/python/encrustable/
Project-URL: Homepage, https://gitlab.com/arcanery/python/encrustable
Project-URL: Repository, https://gitlab.com/arcanery/python/encrustable
